labs/w5/rtl/fir3_parallel.v
`timescale 1ns/1ps

// Week 5: registered parallel 3-tap FIR, beginner-level plain Verilog.
// Coefficients: h0 = 1, h1 = 2, h2 = 1.
// On an accepted rising edge, arithmetic uses x_in and the PRE-EDGE d0/d1 values.
// The delay-state width intentionally matches the Week 4 baseline.
module fir3_parallel (
    input  wire              clk,
    input  wire              rst_n,
    input  wire              valid_in,
    input  wire signed [7:0] x_in,
    output reg               valid_out,
    output reg  signed [9:0] y_out
);

    // Keep Week 4's 10-bit signed sample-history convention so Week 4/5
    // resource and timing comparisons do not silently change state width.
    reg signed [9:0] d0, d1, d2;

    // Explicit sign extension of the signed 8-bit input before use/storage.
    wire signed [9:0] x_ext;
    assign x_ext = {{2{x_in[7]}}, x_in};

    wire signed [9:0] p0, p1, p2;
    wire signed [9:0] s0;
    wire signed [9:0] y_next;

    // h = [1, 2, 1]
    assign p0 = x_ext;
    assign p1 = d0 <<< 1;   // +2*d0; d0 always stores sign-extended INT8 samples
    assign p2 = d1;

    // Two explicit two-input additions.
    assign s0     = p0 + p1;
    assign y_next = s0 + p2;

    always @(posedge clk or negedge rst_n) begin
        if (!rst_n) begin
            d0        <= 10'sd0;
            d1        <= 10'sd0;
            d2        <= 10'sd0;
            y_out     <= 10'sd0;
            valid_out <= 1'b0;
        end else if (valid_in) begin
            // Simultaneous nonblocking delay-line update.
            d2 <= d1;
            d1 <= d0;
            d0 <= x_ext;

            // y_next uses x_in, d0_old, d1_old on this accepted edge.
            y_out     <= y_next;
            valid_out <= 1'b1;
        end else begin
            // Delay line and y_out hold when input is invalid.
            valid_out <= 1'b0;
        end
    end

endmodule

labs/w5/tb/tb_fir3_parallel.v
`timescale 1ns/1ps

module tb_fir3_parallel;

    reg clk;
    reg rst_n;
    reg valid_in;
    reg signed [7:0] x_in;
    wire valid_out;
    wire signed [9:0] y_out;

    integer errors;

    fir3_parallel dut (
        .clk(clk),
        .rst_n(rst_n),
        .valid_in(valid_in),
        .x_in(x_in),
        .valid_out(valid_out),
        .y_out(y_out)
    );

    initial begin
        clk = 1'b0;
        forever #5 clk = ~clk;
    end

    task expect_state;
        input signed [9:0] e_d0;
        input signed [9:0] e_d1;
        input signed [9:0] e_d2;
        input              e_valid;
        input signed [9:0] e_y;
        input integer      check_y;
        input [8*48-1:0]   label;
        begin
            #1;
            if (dut.d0 !== e_d0 || dut.d1 !== e_d1 || dut.d2 !== e_d2) begin
                $display("[FAIL] %0s delay state: d0=%0d d1=%0d d2=%0d expected %0d %0d %0d",
                         label, dut.d0, dut.d1, dut.d2, e_d0, e_d1, e_d2);
                errors = errors + 1;
            end
            if (valid_out !== e_valid) begin
                $display("[FAIL] %0s valid_out=%0b expected %0b", label, valid_out, e_valid);
                errors = errors + 1;
            end
            if (check_y && y_out !== e_y) begin
                $display("[FAIL] %0s y_out=%0d expected %0d", label, y_out, e_y);
                errors = errors + 1;
            end
            if (dut.d0 === e_d0 && dut.d1 === e_d1 && dut.d2 === e_d2 &&
                valid_out === e_valid && (!check_y || y_out === e_y))
                $display("[PASS] %0s d0=%0d d1=%0d d2=%0d y=%0d valid=%0b",
                         label, dut.d0, dut.d1, dut.d2, y_out, valid_out);
        end
    endtask

    task drive_at_negedge;
        input signed [7:0] sample;
        input              v;
        begin
            @(negedge clk);
            x_in = sample;
            valid_in = v;
        end
    endtask

    initial begin
        errors = 0;
        rst_n = 1'b0;
        valid_in = 1'b0;
        x_in = 8'sd0;

        $dumpfile("waves/fir3_parallel.vcd");
        $dumpvars(0, tb_fir3_parallel);

        // Asynchronous active-low reset establishes a known state.
        #2;
        expect_state(10'sd0, 10'sd0, 10'sd0, 1'b0, 10'sd0, 1, "reset asserted");

        // Release reset away from a rising edge; release itself must not capture input.
        @(negedge clk);
        rst_n = 1'b1;
        x_in = 8'sd77;
        valid_in = 1'b1;
        #1;
        expect_state(10'sd0, 10'sd0, 10'sd0, 1'b0, 10'sd0, 1, "reset release no capture");
        valid_in = 1'b0;

        // Accept 1 -> y=1.
        drive_at_negedge(8'sd1, 1'b1);
        @(posedge clk);
        expect_state(10'sd1, 10'sd0, 10'sd0, 1'b1, 10'sd1, 1, "accept x=1");

        // Accept 2 -> y=4.
        drive_at_negedge(8'sd2, 1'b1);
        @(posedge clk);
        expect_state(10'sd2, 10'sd1, 10'sd0, 1'b1, 10'sd4, 1, "accept x=2");

        // Invalid x=99 must be ignored; delay state and y_out hold, valid_out=0.
        drive_at_negedge(8'sd99, 1'b0);
        @(posedge clk);
        expect_state(10'sd2, 10'sd1, 10'sd0, 1'b0, 10'sd4, 1, "hold invalid x=99");

        // Continue accepted sequence.
        drive_at_negedge(8'sd3, 1'b1);
        @(posedge clk);
        expect_state(10'sd3, 10'sd2, 10'sd1, 1'b1, 10'sd8, 1, "accept x=3");

        drive_at_negedge(8'sd4, 1'b1);
        @(posedge clk);
        expect_state(10'sd4, 10'sd3, 10'sd2, 1'b1, 10'sd12, 1, "accept x=4");

        drive_at_negedge(8'sd5, 1'b1);
        @(posedge clk);
        expect_state(10'sd5, 10'sd4, 10'sd3, 1'b1, 10'sd16, 1, "accept x=5");

        drive_at_negedge(8'sd0, 1'b0);
        @(posedge clk);
        expect_state(10'sd5, 10'sd4, 10'sd3, 1'b0, 10'sd16, 1, "post-sequence hold");

        if (errors == 0)
            $display("[RESULT] FIR3_PARALLEL TEST PASSED");
        else
            $display("[RESULT] FIR3_PARALLEL TEST FAILED with %0d error(s)", errors);

        #4;
        $finish;
    end

endmodule

labs/w5/build/xsim/fir3_parallel/waves/fir3_parallel.vcd
$date
   Thu Oct  8 15:25:08 2026
$end

$version
  2025.2
  $dumpfile ("waves/fir3_parallel.vcd") 
$end

$timescale
  1ps
$end

$scope module tb_fir3_parallel $end
$var reg 1 ! clk $end
$var reg 1 " rst_n $end
$var reg 1 # valid_in $end
$var reg 8 $ x_in [7:0] $end
$var wire 1 % valid_out $end
$var wire 10 & y_out [9:0] $end
$var integer 32 ' errors [31:0] $end
$scope module dut $end
$var wire 1 ( clk $end
$var wire 1 ) rst_n $end
$var wire 1 * valid_in $end
$var wire 8 + x_in [7:0] $end
$var reg 1 , valid_out $end
$var reg 10 - y_out [9:0] $end
$var reg 10 . d0 [9:0] $end
$var reg 10 / d1 [9:0] $end
$var reg 10 0 d2 [9:0] $end
$var wire 10 1 x_ext [9:0] $end
$var wire 10 2 p0 [9:0] $end
$var wire 10 3 p1 [9:0] $end
$var wire 10 4 p2 [9:0] $end
$var wire 10 5 s0 [9:0] $end
$var wire 10 6 y_next [9:0] $end
$upscope $end
$scope task expect_state $end
$var reg 10 7 e_d0 [9:0] $end
$var reg 10 8 e_d1 [9:0] $end
$var reg 10 9 e_d2 [9:0] $end
$var reg 1 : e_valid $end
$var reg 10 ; e_y [9:0] $end
$var integer 32 < check_y [31:0] $end
$var reg 384 = label [383:0] $end
$upscope $end
$scope task drive_at_negedge $end
$var reg 8 > sample [7:0] $end
$var reg 1 ? v $end
$upscope $end
$upscope $end
$enddefinitions $end

#0
$dumpvars
0!
0"
0#
b0 $
0%
b0 &
b0 '
0(
0)
0*
b0 +
0,
b0 -
b0 .
b0 /
b0 0
b0 1
b0 2
b0 3
b0 4
b0 5
b0 6
bx 7
bx 8
bx 9
x:
bx ;
bx <
bx =
bx >
x?
$end

#2000
b0 7
b0 8
b0 9
0:
b0 ;
b1 <
b111001001100101011100110110010101110100001000000110000101110011011100110110010101110010011101000110010101100100 =

#5000
1!
1(

#10000
0!
1"
1#
b1001101 $
0(
1)
1*
b1001101 +
b1001101 1
b1001101 2
b1001101 5
b1001101 6

#11000
b11100100110010101110011011001010111010000100000011100100110010101101100011001010110000101110011011001010010000001101110011011110010000001100011011000010111000001110100011101010111001001100101 =

#12000
0#
0*
b1 >
1?

#15000
1!
1(

#20000
0!
1#
b1 $
0(
1*
b1 +
b1 1
b1 2
b1 5
b1 6

#25000
1!
1%
b1 &
1(
1,
b1 -
b1 .
b10 3
b11 5
b11 6
b1 7
1:
b1 ;
b1100001011000110110001101100101011100000111010000100000011110000011110100110001 =

#26000
b10 >

#30000
0!
b10 $
0(
b10 +
b10 1
b10 2
b100 5
b100 6

#35000
1!
b100 &
1(
b100 -
b10 .
b1 /
b100 3
b1 4
b110 5
b111 6
b10 7
b1 8
b100 ;
b1100001011000110110001101100101011100000111010000100000011110000011110100110010 =

#36000
b1100011 >
0?

#40000
0!
0#
b1100011 $
0(
0*
b1100011 +
b1100011 1
b1100011 2
b1100111 5
b1101000 6

#45000
1!
0%
1(
0,
0:
b110100001101111011011000110010000100000011010010110111001110110011000010110110001101001011001000010000001111000001111010011100100111001 =

#46000
b11 >
1?

#50000
0!
1#
b11 $
0(
1*
b11 +
b11 1
b11 2
b111 5
b1000 6

#55000
1!
1%
b1000 &
1(
1,
b1000 -
b11 .
b10 /
b1 0
b110 3
b10 4
b1001 5
b1011 6
b11 7
b10 8
b1 9
1:
b1000 ;
b1100001011000110110001101100101011100000111010000100000011110000011110100110011 =

#56000
b100 >

#60000
0!
b100 $
0(
b100 +
b100 1
b100 2
b1010 5
b1100 6

#65000
1!
b1100 &
1(
b1100 -
b100 .
b11 /
b10 0
b1000 3
b11 4
b1100 5
b1111 6
b100 7
b11 8
b10 9
b1100 ;
b1100001011000110110001101100101011100000111010000100000011110000011110100110100 =

#66000
b101 >

#70000
0!
b101 $
0(
b101 +
b101 1
b101 2
b1101 5
b10000 6

#75000
1!
b10000 &
1(
b10000 -
b101 .
b100 /
b11 0
b1010 3
b100 4
b1111 5
b10011 6
b101 7
b100 8
b11 9
b10000 ;
b1100001011000110110001101100101011100000111010000100000011110000011110100110101 =

#76000
b0 >
0?

#80000
0!
0#
b0 $
0(
0*
b0 +
b0 1
b0 2
b1010 5
b1110 6

#85000
1!
0%
1(
0,
0:
b11100000110111101110011011101000010110101110011011001010111000101110101011001010110111001100011011001010010000001101000011011110110110001100100 =

