labs/w4/rtl/fir3_seq.v
`timescale 1ns/1ps

// Week 4 baseline: sequential sample history + combinational FIR arithmetic.
// Coefficients are fixed at h = [1, 2, 1].
// d0 = newest accepted sample, d1 = previous accepted sample,
// d2 = sample from two accepted inputs earlier.
module fir3_seq (
    input  wire                    clk,
    input  wire                    rst_n,
    input  wire                    valid_in,
    input  wire signed [7:0]       x_in,
    output reg                     valid_out,
    output wire signed [9:0]       y_out
);

    // 10-bit signed state is deliberately wider than x_in so the complete
    // h=[1,2,1] result range (-512..508) can be represented without overflow.
    reg signed [9:0] d0;
    reg signed [9:0] d1;
    reg signed [9:0] d2;

    // Explicit sign extension of the 8-bit input before storing it.
    wire signed [9:0] x_ext;
    assign x_ext = {{2{x_in[7]}}, x_in};

    // Exposed arithmetic nodes are useful for waveform-based debugging.
    wire signed [9:0] p0;
    wire signed [9:0] p1;
    wire signed [9:0] p2;
    wire signed [9:0] s0;

    assign p0 = d0;
    assign p1 = d1 <<< 1;   // coefficient h1 = 2
    assign p2 = d2;
    assign s0 = p0 + p1;
    assign y_out = s0 + p2;

    // Sample history and valid_out are sequential.
    // Reset is asynchronous and active low.
    always @(posedge clk or negedge rst_n) begin
        if (!rst_n) begin
            d0        <= 10'sd0;
            d1        <= 10'sd0;
            d2        <= 10'sd0;
            valid_out <= 1'b0;
        end else if (valid_in) begin
            d2        <= d1;
            d1        <= d0;
            d0        <= x_ext;
            valid_out <= 1'b1;
        end else begin
            // No assignments to d0/d1/d2: the sample history holds.
            valid_out <= 1'b0;
        end
    end

endmodule

labs/w4/tb/tb_fir3_seq.v
`timescale 1ns/1ps

module tb_fir3_seq;

    reg clk;
    reg rst_n;
    reg valid_in;
    reg signed [7:0] x_in;

    wire valid_out;
    wire signed [9:0] y_out;

    integer errors;

    fir3_seq dut (
        .clk       (clk),
        .rst_n     (rst_n),
        .valid_in  (valid_in),
        .x_in      (x_in),
        .valid_out (valid_out),
        .y_out     (y_out)
    );

    initial clk = 1'b0;
    always #5 clk = ~clk;  // 10 ns period; rising edges at 5,15,25,... ns

    task check_state;
        input signed [9:0] exp_d0;
        input signed [9:0] exp_d1;
        input signed [9:0] exp_d2;
        input signed [9:0] exp_y;
        input              exp_valid;
        input [8*48-1:0]   label;
        begin
            #1;
            if ((dut.d0 !== exp_d0) ||
                (dut.d1 !== exp_d1) ||
                (dut.d2 !== exp_d2) ||
                (y_out  !== exp_y)  ||
                (valid_out !== exp_valid)) begin
                $display("[FAIL] %0s t=%0t d0=%0d d1=%0d d2=%0d y=%0d valid=%0b | expected d0=%0d d1=%0d d2=%0d y=%0d valid=%0b",
                         label, $time, dut.d0, dut.d1, dut.d2, y_out, valid_out,
                         exp_d0, exp_d1, exp_d2, exp_y, exp_valid);
                errors = errors + 1;
            end else begin
                $display("[PASS] %0s t=%0t d0=%0d d1=%0d d2=%0d y=%0d valid=%0b",
                         label, $time, dut.d0, dut.d1, dut.d2, y_out, valid_out);
            end
        end
    endtask

    task drive_before_rise;
        input signed [7:0] sample;
        input              v;
        begin
            @(negedge clk);
            x_in     = sample;
            valid_in = v;
        end
    endtask

    initial begin
        errors   = 0;
        rst_n    = 1'b0;
        valid_in = 1'b0;
        x_in     = 8'sd0;

        $dumpfile("waves/fir3_seq.vcd");
        $dumpvars(0, tb_fir3_seq);

        // Reset is asserted from time 0. Check known state after a reset edge.
        #2;
        check_state(10'sd0, 10'sd0, 10'sd0, 10'sd0, 1'b0, "reset asserted");

        // Release reset at 22 ns, strictly between rising edges at 15 and 25 ns.
        #19;
        rst_n = 1'b1;
        #1;
        if ((dut.d0 !== 10'sd0) || (dut.d1 !== 10'sd0) ||
            (dut.d2 !== 10'sd0) || (y_out !== 10'sd0) ||
            (valid_out !== 1'b0)) begin
            $display("[FAIL] reset release changed state/captured input at t=%0t", $time);
            errors = errors + 1;
        end else begin
            $display("[PASS] reset release does not capture input at t=%0t", $time);
        end

        // Rising edge at 25 ns occurs with valid_in=0: state must still hold zero.
        @(posedge clk);
        check_state(10'sd0, 10'sd0, 10'sd0, 10'sd0, 1'b0, "post-reset hold");

        // Accepted sample sequence is 1,2,3,4,5.  The 99 at 55 ns is invalid
        // and must not advance the delay line.
        drive_before_rise(8'sd1, 1'b1);   // drive at 30 ns, accept at 35 ns
        @(posedge clk);
        check_state(10'sd1, 10'sd0, 10'sd0, 10'sd1, 1'b1, "accept x=1");

        drive_before_rise(8'sd2, 1'b1);   // accept at 45 ns
        @(posedge clk);
        check_state(10'sd2, 10'sd1, 10'sd0, 10'sd4, 1'b1, "accept x=2");

        drive_before_rise(8'sd99, 1'b0);  // edge at 55 ns: hold
        @(posedge clk);
        check_state(10'sd2, 10'sd1, 10'sd0, 10'sd4, 1'b0, "ignore invalid x=99");

        drive_before_rise(8'sd3, 1'b1);   // accept at 65 ns
        @(posedge clk);
        check_state(10'sd3, 10'sd2, 10'sd1, 10'sd8, 1'b1, "accept x=3");

        drive_before_rise(8'sd4, 1'b1);   // accept at 75 ns
        @(posedge clk);
        check_state(10'sd4, 10'sd3, 10'sd2, 10'sd12, 1'b1, "accept x=4");

        drive_before_rise(8'sd5, 1'b1);   // accept at 85 ns
        @(posedge clk);
        check_state(10'sd5, 10'sd4, 10'sd3, 10'sd16, 1'b1, "accept x=5");

        // One final invalid cycle proves state hold and valid_out deassertion.
        drive_before_rise(8'sd0, 1'b0);   // edge at 95 ns
        @(posedge clk);
        check_state(10'sd5, 10'sd4, 10'sd3, 10'sd16, 1'b0, "final hold");

        if (errors == 0) begin
            $display("[RESULT] FIR3_SEQ TEST PASSED");
        end else begin
            $display("[RESULT] FIR3_SEQ TEST FAILED errors=%0d", errors);
        end

        #4;
        $finish;
    end

endmodule

labs/w4/waves/fir3_seq.vcd
$date
   Fri Oct  9 00:28:45 2026
$end

$version
  2025.2
  $dumpfile ("waves/fir3_seq.vcd") 
$end

$timescale
  1ps
$end

$scope module tb_fir3_seq $end
$var reg 1 ! clk $end
$var reg 1 " rst_n $end
$var reg 1 # valid_in $end
$var reg 8 $ x_in [7:0] $end
$var wire 1 % valid_out $end
$var wire 10 & y_out [9:0] $end
$var integer 32 ' errors [31:0] $end
$scope module dut $end
$var wire 1 ( clk $end
$var wire 1 ) rst_n $end
$var wire 1 * valid_in $end
$var wire 8 + x_in [7:0] $end
$var reg 1 , valid_out $end
$var wire 10 & y_out [9:0] $end
$var reg 10 - d0 [9:0] $end
$var reg 10 . d1 [9:0] $end
$var reg 10 / d2 [9:0] $end
$var wire 10 0 x_ext [9:0] $end
$var wire 10 1 p0 [9:0] $end
$var wire 10 2 p1 [9:0] $end
$var wire 10 3 p2 [9:0] $end
$var wire 10 4 s0 [9:0] $end
$upscope $end
$scope task check_state $end
$var reg 10 5 exp_d0 [9:0] $end
$var reg 10 6 exp_d1 [9:0] $end
$var reg 10 7 exp_d2 [9:0] $end
$var reg 10 8 exp_y [9:0] $end
$var reg 1 9 exp_valid $end
$var reg 384 : label [383:0] $end
$upscope $end
$scope task drive_before_rise $end
$var reg 8 ; sample [7:0] $end
$var reg 1 < v $end
$upscope $end
$upscope $end
$enddefinitions $end

#0
$dumpvars
0!
0"
0#
b0 $
0%
b0 &
b0 '
0(
0)
0*
b0 +
0,
b0 -
b0 .
b0 /
b0 0
b0 1
b0 2
b0 3
b0 4
bx 5
bx 6
bx 7
bx 8
x9
bx :
bx ;
x<
$end

#2000
b0 5
b0 6
b0 7
b0 8
09
b111001001100101011100110110010101110100001000000110000101110011011100110110010101110010011101000110010101100100 :

#5000
1!
1(

#10000
0!
0(

#15000
1!
1(

#20000
0!
0(

#22000
1"
1)

#25000
1!
1(
b11100000110111101110011011101000010110101110010011001010111001101100101011101000010000001101000011011110110110001100100 :

#26000
b1 ;
1<

#30000
0!
1#
b1 $
0(
1*
b1 +
b1 0

#35000
1!
1%
b1 &
1(
1,
b1 -
b1 1
b1 4
b1 5
b1 8
19
b1100001011000110110001101100101011100000111010000100000011110000011110100110001 :

#36000
b10 ;

#40000
0!
b10 $
0(
b10 +
b10 0

#45000
1!
b100 &
1(
b10 -
b1 .
b10 1
b10 2
b100 4
b10 5
b1 6
b100 8
b1100001011000110110001101100101011100000111010000100000011110000011110100110010 :

#46000
b1100011 ;
0<

#50000
0!
0#
b1100011 $
0(
0*
b1100011 +
b1100011 0

#55000
1!
0%
1(
0,
09
b1101001011001110110111001101111011100100110010100100000011010010110111001110110011000010110110001101001011001000010000001111000001111010011100100111001 :

#56000
b11 ;
1<

#60000
0!
1#
b11 $
0(
1*
b11 +
b11 0

#65000
1!
1%
b1000 &
1(
1,
b11 -
b10 .
b1 /
b11 1
b100 2
b1 3
b111 4
b11 5
b10 6
b1 7
b1000 8
19
b1100001011000110110001101100101011100000111010000100000011110000011110100110011 :

#66000
b100 ;

#70000
0!
b100 $
0(
b100 +
b100 0

#75000
1!
b1100 &
1(
b100 -
b11 .
b10 /
b100 1
b110 2
b10 3
b1010 4
b100 5
b11 6
b10 7
b1100 8
b1100001011000110110001101100101011100000111010000100000011110000011110100110100 :

#76000
b101 ;

#80000
0!
b101 $
0(
b101 +
b101 0

#85000
1!
b10000 &
1(
b101 -
b100 .
b11 /
b101 1
b1000 2
b11 3
b1101 4
b101 5
b100 6
b11 7
b10000 8
b1100001011000110110001101100101011100000111010000100000011110000011110100110101 :

#86000
b0 ;
0<

#90000
0!
0#
b0 $
0(
0*
b0 +
b0 0

#95000
1!
0%
1(
0,
09
b1100110011010010110111001100001011011000010000001101000011011110110110001100100 :

