labs/w7/rtl/fir3_pipe2.v
`timescale 1ns/1ps

// Week 5: one-cycle pipelined 3-tap FIR, beginner-level plain Verilog.
// Stage 1 stores products. Stage 2 adds the stored products and registers y_out.
// Coefficients: h0 = 1, h1 = 2, h2 = 1.
// The delay-state width intentionally matches the Week 4 baseline.
module fir3_pipe2 (
    input  wire              clk,
    input  wire              rst_n,
    input  wire              valid_in,
    input  wire signed [7:0] x_in,
    output reg               valid_out,
    output reg  signed [9:0] y_out
);

    // Same 10-bit signed sample-history convention as Week 4.
    reg signed [9:0] d0, d1, d2;

    wire signed [9:0] x_ext;
    assign x_ext = {{2{x_in[7]}}, x_in};

    reg signed [9:0] p0_s1, p1_s1, p2_s1;
    reg              valid_s1;

    wire signed [9:0] s0_s1;
    wire signed [9:0] y_s1;

    // Stage-2 combinational adder structure from registered products.
    assign s0_s1 = p0_s1 + p1_s1;
    assign y_s1  = s0_s1 + p2_s1;

    always @(posedge clk or negedge rst_n) begin
        if (!rst_n) begin
            d0        <= 10'sd0;
            d1        <= 10'sd0;
            d2        <= 10'sd0;
            p0_s1     <= 10'sd0;
            p1_s1     <= 10'sd0;
            p2_s1     <= 10'sd0;
            y_out     <= 10'sd0;
            valid_s1  <= 1'b0;
            valid_out <= 1'b0;
        end else begin
            // Stage 2 consumes the previous cycle's Stage-1 values.
            if (valid_s1)
                y_out <= y_s1;
            valid_out <= valid_s1;

            // Stage-1 valid follows this cycle's accepted input.
            valid_s1 <= valid_in;

            if (valid_in) begin
                // Products use x_in and PRE-EDGE d0/d1 values.
                p0_s1 <= x_ext;
                p1_s1 <= d0 <<< 1;
                p2_s1 <= d1;

                // Delay line advances only on accepted rising edges.
                d2 <= d1;
                d1 <= d0;
                d0 <= x_ext;
            end
            // When valid_in=0, product registers and d0/d1/d2 hold.
        end
    end

endmodule

labs/w6/tb/tb_fir3_pipe2_signed.v
`timescale 1ns/1ps

// Signed-width boundary regression for the Week 5 one-cycle pipeline.
module tb_fir3_pipe2_signed;
    reg clk;
    reg rst_n;
    reg valid_in;
    reg signed [7:0] x_in;
    wire valid_out;
    wire signed [9:0] y_out;
    integer errors;

    fir3_pipe2 dut (
        .clk(clk), .rst_n(rst_n), .valid_in(valid_in), .x_in(x_in),
        .valid_out(valid_out), .y_out(y_out)
    );

    initial clk = 1'b0;
    always #5 clk = ~clk;

    task drive;
        input signed [7:0] sample;
        input v;
        begin
            @(negedge clk);
            x_in = sample;
            valid_in = v;
        end
    endtask

    task expect_output;
        input e_valid;
        input signed [9:0] e_y;
        input [8*48-1:0] label;
        begin
            #1;
            if (valid_out !== e_valid || y_out !== e_y) begin
                $display("[FAIL] %0s y=%0d valid=%0b expected=%0d/%0b",
                         label, y_out, valid_out, e_y, e_valid);
                errors = errors + 1;
            end else begin
                $display("[PASS] %0s y=%0d valid=%0b", label, y_out, valid_out);
            end
        end
    endtask

    initial begin
        errors = 0;
        rst_n = 1'b0;
        valid_in = 1'b0;
        x_in = 8'sd0;

        $dumpfile("waves/fir3_pipe2_signed.vcd");
        $dumpvars(0, tb_fir3_pipe2_signed);

        #12;
        rst_n = 1'b1;

        // First -128 is accepted into Stage 1; no output yet.
        drive(8'sh80, 1'b1);
        @(posedge clk);
        expect_output(1'b0, 10'sd0, "signed E1 no output yet");

        // Second accepted -128 emits FIR result for the first accepted sample.
        drive(8'sh80, 1'b1);
        @(posedge clk);
        expect_output(1'b1, 10'sh380, "signed E2 output -128");

        // Third accepted -128 emits -384.
        drive(8'sh80, 1'b1);
        @(posedge clk);
        expect_output(1'b1, 10'sh280, "signed E3 output -384");

        // Drain emits the exact lower bound -512.
        drive(8'sd0, 1'b0);
        @(posedge clk);
        expect_output(1'b1, 10'sh200, "signed E4 drain output -512");

        // One more invalid edge proves valid_out deasserts and y_out holds.
        drive(8'sd0, 1'b0);
        @(posedge clk);
        expect_output(1'b0, 10'sh200, "signed E5 idle after drain");

        if (errors == 0)
            $display("[RESULT] FIR3_PIPE2 SIGNED TEST PASSED");
        else
            $display("[RESULT] FIR3_PIPE2 SIGNED TEST FAILED with %0d error(s)", errors);

        #4;
        $finish;
    end
endmodule

labs/w5/build/xsim/fir3_pipe2_signed/waves/fir3_pipe2_signed.vcd
$date
   Thu Oct  8 15:25:25 2026
$end

$version
  2025.2
  $dumpfile ("waves/fir3_pipe2_signed.vcd") 
$end

$timescale
  1ps
$end

$scope module tb_fir3_pipe2_signed $end
$var reg 1 ! clk $end
$var reg 1 " rst_n $end
$var reg 1 # valid_in $end
$var reg 8 $ x_in [7:0] $end
$var wire 1 % valid_out $end
$var wire 10 & y_out [9:0] $end
$var integer 32 ' errors [31:0] $end
$scope module dut $end
$var wire 1 ( clk $end
$var wire 1 ) rst_n $end
$var wire 1 * valid_in $end
$var wire 8 + x_in [7:0] $end
$var reg 1 , valid_out $end
$var reg 10 - y_out [9:0] $end
$var reg 10 . d0 [9:0] $end
$var reg 10 / d1 [9:0] $end
$var reg 10 0 d2 [9:0] $end
$var wire 10 1 x_ext [9:0] $end
$var reg 10 2 p0_s1 [9:0] $end
$var reg 10 3 p1_s1 [9:0] $end
$var reg 10 4 p2_s1 [9:0] $end
$var reg 1 5 valid_s1 $end
$var wire 10 6 s0_s1 [9:0] $end
$var wire 10 7 y_s1 [9:0] $end
$upscope $end
$scope task drive $end
$var reg 8 8 sample [7:0] $end
$var reg 1 9 v $end
$upscope $end
$scope task expect_output $end
$var reg 1 : e_valid $end
$var reg 10 ; e_y [9:0] $end
$var reg 384 < label [383:0] $end
$upscope $end
$upscope $end
$enddefinitions $end

#0
$dumpvars
0!
0"
0#
b0 $
0%
b0 &
b0 '
0(
0)
0*
b0 +
0,
b0 -
b0 .
b0 /
b0 0
b0 1
b0 2
b0 3
b0 4
05
b0 6
b0 7
bx 8
x9
x:
bx ;
bx <
$end

#5000
1!
1(

#10000
0!
0(

#12000
1"
1)
b10000000 8
19

#15000
1!
1(

#20000
0!
1#
b10000000 $
0(
1*
b10000000 +
b1110000000 1

#25000
1!
1(
b1110000000 .
b1110000000 2
15
b1110000000 6
b1110000000 7
0:
b0 ;
b111001101101001011001110110111001100101011001000010000001000101001100010010000001101110011011110010000001101111011101010111010001110000011101010111010000100000011110010110010101110100 <

#30000
0!
0(

#35000
1!
1%
b1110000000 &
1(
1,
b1110000000 -
b1110000000 /
b1100000000 3
b1010000000 6
b1010000000 7
1:
b1110000000 ;
b11100110110100101100111011011100110010101100100001000000100010100110010001000000110111101110101011101000111000001110101011101000010000000101101001100010011001000111000 <

#40000
0!
0(

#45000
1!
b1010000000 &
1(
b1010000000 -
b1110000000 0
b1110000000 4
b1000000000 7
b1010000000 ;
b11100110110100101100111011011100110010101100100001000000100010100110011001000000110111101110101011101000111000001110101011101000010000000101101001100110011100000110100 <

#46000
b0 8
09

#50000
0!
0#
b0 $
0(
0*
b0 +
b0 1

#55000
1!
b1000000000 &
1(
b1000000000 -
05
b1000000000 ;
b11100110110100101100111011011100110010101100100001000000100010100110100001000000110010001110010011000010110100101101110001000000110111101110101011101000111000001110101011101000010000000101101001101010011000100110010 <

#60000
0!
0(

#65000
1!
0%
1(
0,
0:
b111001101101001011001110110111001100101011001000010000001000101001101010010000001101001011001000110110001100101001000000110000101100110011101000110010101110010001000000110010001110010011000010110100101101110 <

