labs/w5/rtl/fir3_parallel.v
`timescale 1ns/1ps

// Week 5: registered parallel 3-tap FIR, beginner-level plain Verilog.
// Coefficients: h0 = 1, h1 = 2, h2 = 1.
// On an accepted rising edge, arithmetic uses x_in and the PRE-EDGE d0/d1 values.
// The delay-state width intentionally matches the Week 4 baseline.
module fir3_parallel (
    input  wire              clk,
    input  wire              rst_n,
    input  wire              valid_in,
    input  wire signed [7:0] x_in,
    output reg               valid_out,
    output reg  signed [9:0] y_out
);

    // Keep Week 4's 10-bit signed sample-history convention so Week 4/5
    // resource and timing comparisons do not silently change state width.
    reg signed [9:0] d0, d1, d2;

    // Explicit sign extension of the signed 8-bit input before use/storage.
    wire signed [9:0] x_ext;
    assign x_ext = {{2{x_in[7]}}, x_in};

    wire signed [9:0] p0, p1, p2;
    wire signed [9:0] s0;
    wire signed [9:0] y_next;

    // h = [1, 2, 1]
    assign p0 = x_ext;
    assign p1 = d0 <<< 1;   // +2*d0; d0 always stores sign-extended INT8 samples
    assign p2 = d1;

    // Two explicit two-input additions.
    assign s0     = p0 + p1;
    assign y_next = s0 + p2;

    always @(posedge clk or negedge rst_n) begin
        if (!rst_n) begin
            d0        <= 10'sd0;
            d1        <= 10'sd0;
            d2        <= 10'sd0;
            y_out     <= 10'sd0;
            valid_out <= 1'b0;
        end else if (valid_in) begin
            // Simultaneous nonblocking delay-line update.
            d2 <= d1;
            d1 <= d0;
            d0 <= x_ext;

            // y_next uses x_in, d0_old, d1_old on this accepted edge.
            y_out     <= y_next;
            valid_out <= 1'b1;
        end else begin
            // Delay line and y_out hold when input is invalid.
            valid_out <= 1'b0;
        end
    end

endmodule

labs/w5/tb/tb_fir3_parallel_signed.v
`timescale 1ns/1ps

// Signed-width boundary regression for the Week 5 registered-parallel FIR.
module tb_fir3_parallel_signed;
    reg clk;
    reg rst_n;
    reg valid_in;
    reg signed [7:0] x_in;
    wire valid_out;
    wire signed [9:0] y_out;
    integer errors;

    fir3_parallel dut (
        .clk(clk), .rst_n(rst_n), .valid_in(valid_in), .x_in(x_in),
        .valid_out(valid_out), .y_out(y_out)
    );

    initial clk = 1'b0;
    always #5 clk = ~clk;

    task accept_and_check;
        input signed [7:0] sample;
        input signed [9:0] expected;
        begin
            @(negedge clk);
            x_in = sample;
            valid_in = 1'b1;
            @(posedge clk);
            #1;
            if (y_out !== expected || valid_out !== 1'b1) begin
                $display("[FAIL] signed parallel sample=%0d y=%0d valid=%0b expected=%0d/1",
                         sample, y_out, valid_out, expected);
                errors = errors + 1;
            end else begin
                $display("[PASS] signed parallel sample=%0d y=%0d", sample, y_out);
            end
        end
    endtask

    initial begin
        errors = 0;
        rst_n = 1'b0;
        valid_in = 1'b0;
        x_in = 8'sd0;

        $dumpfile("waves/fir3_parallel_signed.vcd");
        $dumpvars(0, tb_fir3_parallel_signed);

        #12;
        rst_n = 1'b1;

        // Repeated minimum INT8 input reaches the exact -512 FIR output bound.
        accept_and_check(8'sh80, 10'sh380);  // -128
        accept_and_check(8'sh80, 10'sh280);  // -384
        accept_and_check(8'sh80, 10'sh200);  // -512

        @(negedge clk);
        valid_in = 1'b0;
        x_in = 8'sd0;
        @(posedge clk);
        #1;
        if (valid_out !== 1'b0 || y_out !== 10'sh200) begin
            $display("[FAIL] signed parallel invalid hold y=%0d valid=%0b", y_out, valid_out);
            errors = errors + 1;
        end else begin
            $display("[PASS] signed parallel invalid hold preserves -512 and deasserts valid");
        end

        if (errors == 0)
            $display("[RESULT] FIR3_PARALLEL SIGNED TEST PASSED");
        else
            $display("[RESULT] FIR3_PARALLEL SIGNED TEST FAILED with %0d error(s)", errors);

        #4;
        $finish;
    end
endmodule

labs/w5/build/xsim/fir3_parallel_signed/waves/fir3_parallel_signed.vcd
$date
   Thu Oct  8 15:25:13 2026
$end

$version
  2025.2
  $dumpfile ("waves/fir3_parallel_signed.vcd") 
$end

$timescale
  1ps
$end

$scope module tb_fir3_parallel_signed $end
$var reg 1 ! clk $end
$var reg 1 " rst_n $end
$var reg 1 # valid_in $end
$var reg 8 $ x_in [7:0] $end
$var wire 1 % valid_out $end
$var wire 10 & y_out [9:0] $end
$var integer 32 ' errors [31:0] $end
$scope module dut $end
$var wire 1 ( clk $end
$var wire 1 ) rst_n $end
$var wire 1 * valid_in $end
$var wire 8 + x_in [7:0] $end
$var reg 1 , valid_out $end
$var reg 10 - y_out [9:0] $end
$var reg 10 . d0 [9:0] $end
$var reg 10 / d1 [9:0] $end
$var reg 10 0 d2 [9:0] $end
$var wire 10 1 x_ext [9:0] $end
$var wire 10 2 p0 [9:0] $end
$var wire 10 3 p1 [9:0] $end
$var wire 10 4 p2 [9:0] $end
$var wire 10 5 s0 [9:0] $end
$var wire 10 6 y_next [9:0] $end
$upscope $end
$scope task accept_and_check $end
$var reg 8 7 sample [7:0] $end
$var reg 10 8 expected [9:0] $end
$upscope $end
$upscope $end
$enddefinitions $end

#0
$dumpvars
0!
0"
0#
b0 $
0%
b0 &
b0 '
0(
0)
0*
b0 +
0,
b0 -
b0 .
b0 /
b0 0
b0 1
b0 2
b0 3
b0 4
b0 5
b0 6
bx 7
bx 8
$end

#5000
1!
1(

#10000
0!
0(

#12000
1"
1)
b10000000 7
b1110000000 8

#15000
1!
1(

#20000
0!
1#
b10000000 $
0(
1*
b10000000 +
b1110000000 1
b1110000000 2
b1110000000 5
b1110000000 6

#25000
1!
1%
b1110000000 &
1(
1,
b1110000000 -
b1110000000 .
b1100000000 3
b1010000000 5
b1010000000 6

#26000
b1010000000 8

#30000
0!
0(

#35000
1!
b1010000000 &
1(
b1010000000 -
b1110000000 /
b1110000000 4
b1000000000 6

#36000
b1000000000 8

#40000
0!
0(

#45000
1!
b1000000000 &
1(
b1000000000 -
b1110000000 0

#50000
0!
0#
b0 $
0(
0*
b0 +
b0 1
b0 2
b1100000000 5
b1010000000 6

#55000
1!
0%
1(
0,

