labs/w3/rtl/fir3_arith.v
// fir3_arith.v
// Week 3 - 3-tap FIR combinational arithmetic reference
// EDA Design Flow Integration
// Plain Verilog-2001, synthesizable combinational RTL
`timescale 1ns/1ps
//
// IMPORTANT:
//   This is NOT the full sequential FIR module for Week 4.
//   d0, d1, and d2 are supplied as already-stored sample values.
//   The purpose here is to make the multiply-and-add structure explicit.

module fir3_arith (
    input  wire signed [7:0]  d0,
    input  wire signed [7:0]  d1,
    input  wire signed [7:0]  d2,
    input  wire signed [7:0]  h0,
    input  wire signed [7:0]  h1,
    input  wire signed [7:0]  h2,
    output wire signed [15:0] p0,
    output wire signed [15:0] p1,
    output wire signed [15:0] p2,
    output wire signed [16:0] s0,
    output wire signed [17:0] y_out
);

// One explicit product per tap.
assign p0 = d0 * h0;
assign p1 = d1 * h1;
assign p2 = d2 * h2;

// Explicit two-adder chain for three products.
// Sign extension is written explicitly so the additions do not silently
// discard a carry/sign bit when the product range grows.
assign s0 = {p0[15], p0} + {p1[15], p1};
assign y_out = {s0[16], s0} + {{2{p2[15]}}, p2};

endmodule

labs/w3/tb/tb_fir3_trace.v
// tb_fir3_trace.v
// Week 3 - Testbench-only FIR state trace and checker
// Plain Verilog testbench
//
// This file deliberately keeps d0/d1/d2 as TESTBENCH state. It demonstrates
// the Week 3 hand-trace convention without providing the full sequential FIR
// DUT that students will write in Week 4.

`timescale 1ns/1ps

module tb_fir3_trace;

reg clk;
reg rst_n;
reg valid_in;
reg signed [7:0] x_in;
reg signed [7:0] d0;
reg signed [7:0] d1;
reg signed [7:0] d2;
reg signed [7:0] old_d0;
reg signed [7:0] old_d1;

reg signed [7:0] h0;
reg signed [7:0] h1;
reg signed [7:0] h2;
wire signed [15:0] p0;
wire signed [15:0] p1;
wire signed [15:0] p2;
wire signed [16:0] s0;
wire signed [17:0] y_out;

integer errors;
integer sample_index;

fir3_arith dut_arith (
    .d0(d0), .d1(d1), .d2(d2),
    .h0(h0), .h1(h1), .h2(h2),
    .p0(p0), .p1(p1), .p2(p2),
    .s0(s0), .y_out(y_out)
);

// 10 ns clock period: rising edges at 5, 15, 25, ... ns.
initial begin
    clk = 1'b0;
    forever #5 clk = ~clk;
end

task accept_and_check;
    input signed [7:0] sample;
    input signed [17:0] expected_y;
    begin
        // Apply the sample away from the active edge.
        @(negedge clk);
        x_in    = sample;
        valid_in = 1'b1;

        // At the next rising edge, emulate the Week 3 state transition
        // using the OLD d0/d1 values explicitly.
        @(posedge clk);
        old_d0 = d0;
        old_d1 = d1;
        d0 = x_in;
        d1 = old_d0;
        d2 = old_d1;

        #1;
        $display("[TRACE] n=%0d x=%0d state[d0,d1,d2]=[%0d,%0d,%0d] p=[%0d,%0d,%0d] y=%0d",
                 sample_index, x_in, d0, d1, d2, p0, p1, p2, y_out);

        if (y_out !== expected_y) begin
            $display("[FAIL] n=%0d expected y=%0d got y=%0d", sample_index, expected_y, y_out);
            errors = errors + 1;
        end else begin
            $display("[PASS] n=%0d expected y=%0d", sample_index, expected_y);
        end

        sample_index = sample_index + 1;
        valid_in = 1'b0;
    end
endtask

initial begin
    $dumpfile("waves/fir3_trace.vcd");
    $dumpvars(0, tb_fir3_trace);

    errors = 0;
    sample_index = 0;
    h0 = 8'sd1;
    h1 = 8'sd2;
    h2 = 8'sd1;

    rst_n = 1'b0;
    valid_in = 1'b0;
    x_in = 0;
    d0 = 0;
    d1 = 0;
    d2 = 0;
    old_d0 = 0;
    old_d1 = 0;

    $display("============================================================");
    $display("Week 3 FIR hand-trace simulation started");
    $display("Reset history begins at state [0,0,0]");
    $display("============================================================");

    // Keep reset asserted through the first rising edge at 5 ns.
    @(posedge clk);
    #1;
    if ((d0 !== 0) || (d1 !== 0) || (d2 !== 0)) begin
        $display("[FAIL] reset state is not [0,0,0]");
        errors = errors + 1;
    end else begin
        $display("[PASS] reset state [d0,d1,d2]=[0,0,0]");
    end

    // Release reset at a falling edge, i.e. between rising edges.
    // Reset release itself does not shift the sample history.
    @(negedge clk);
    rst_n = 1'b1;
    #1;
    if ((d0 !== 0) || (d1 !== 0) || (d2 !== 0)) begin
        $display("[FAIL] state changed at reset release");
        errors = errors + 1;
    end else begin
        $display("[PASS] reset release does not capture a sample");
    end

    // Hand-trace sequence from the Week 3 slides/handout.
    accept_and_check(8'sd1, 18'sd1);
    accept_and_check(8'sd2, 18'sd4);
    accept_and_check(8'sd3, 18'sd8);
    accept_and_check(8'sd0, 18'sd8);
    accept_and_check(8'sd0, 18'sd3);

    $display("============================================================");
    $display("Expected output sequence: 1, 4, 8, 8, 3");
    if (errors == 0)
        $display("[RESULT] FIR3 TRACE TEST PASSED");
    else
        $display("[RESULT] FIR3 TRACE TEST FAILED with %0d error(s)", errors);
    $display("============================================================");

    #10;
    $finish;
end

endmodule

labs/w3/waves/vivado/fir3_trace.vcd
$date
   Thu Sep 24 16:45:33 2026
$end

$version
  2025.2
  $dumpfile ("waves/fir3_trace.vcd") 
$end

$timescale
  1ps
$end

$scope module tb_fir3_trace $end
$var reg 1 ! clk $end
$var reg 1 " rst_n $end
$var reg 1 # valid_in $end
$var reg 8 $ x_in [7:0] $end
$var reg 8 % d0 [7:0] $end
$var reg 8 & d1 [7:0] $end
$var reg 8 ' d2 [7:0] $end
$var reg 8 ( old_d0 [7:0] $end
$var reg 8 ) old_d1 [7:0] $end
$var reg 8 * h0 [7:0] $end
$var reg 8 + h1 [7:0] $end
$var reg 8 , h2 [7:0] $end
$var wire 16 - p0 [15:0] $end
$var wire 16 . p1 [15:0] $end
$var wire 16 / p2 [15:0] $end
$var wire 17 0 s0 [16:0] $end
$var wire 18 1 y_out [17:0] $end
$var integer 32 2 errors [31:0] $end
$var integer 32 3 sample_index [31:0] $end
$scope module dut_arith $end
$var wire 8 4 d0 [7:0] $end
$var wire 8 5 d1 [7:0] $end
$var wire 8 6 d2 [7:0] $end
$var wire 8 7 h0 [7:0] $end
$var wire 8 8 h1 [7:0] $end
$var wire 8 9 h2 [7:0] $end
$var wire 16 - p0 [15:0] $end
$var wire 16 . p1 [15:0] $end
$var wire 16 / p2 [15:0] $end
$var wire 17 0 s0 [16:0] $end
$var wire 18 1 y_out [17:0] $end
$upscope $end
$scope task accept_and_check $end
$var reg 8 : sample [7:0] $end
$var reg 18 ; expected_y [17:0] $end
$upscope $end
$upscope $end
$enddefinitions $end

#0
$dumpvars
0!
0"
0#
b0 $
b0 %
b0 &
b0 '
b0 (
b0 )
b1 *
b10 +
b1 ,
b0 -
b0 .
b0 /
b0 0
b0 1
b0 2
b0 3
b0 4
b0 5
b0 6
b1 7
b10 8
b1 9
bx :
bx ;
$end

#5000
1!

#10000
0!
1"

#11000
b1 :
b1 ;

#15000
1!

#20000
0!
1#
b1 $

#25000
1!
b1 %
b1 -
b1 0
b1 1
b1 4

#26000
0#
b1 3
b10 :
b100 ;

#30000
0!
1#
b10 $

#35000
1!
b10 %
b1 &
b1 (
b10 -
b10 .
b100 0
b100 1
b10 4
b1 5

#36000
0#
b10 3
b11 :
b1000 ;

#40000
0!
1#
b11 $

#45000
1!
b11 %
b10 &
b1 '
b10 (
b1 )
b11 -
b100 .
b1 /
b111 0
b1000 1
b11 4
b10 5
b1 6

#46000
0#
b11 3
b0 :

#50000
0!
1#
b0 $

#55000
1!
b0 %
b11 &
b10 '
b11 (
b10 )
b0 -
b110 .
b10 /
b110 0
b1000 1
b0 4
b11 5
b10 6

#56000
0#
b100 3
b11 ;

#60000
0!
1#

#65000
1!
b0 &
b11 '
b0 (
b11 )
b0 .
b11 /
b0 0
b11 1
b0 5
b11 6

#66000
0#
b101 3

