labs/w2/w2/rtl/reg8.v
// reg8.v
// Week 2 - Small sequential register module
// EDA Design Flow Integration
// Plain Verilog, synthesizable RTL

`timescale 1ns/1ps

module reg8 (
    input  wire       clk,
    input  wire       rst_n,
    input  wire [7:0] d,
    output reg  [7:0] q
);

// Active-low asynchronous reset.
// After reset is released, q captures d only on a rising clock edge.
always @(posedge clk or negedge rst_n) begin
    if (!rst_n)
        q <= 8'h00;
    else
        q <= d;
end

endmodule

labs/w2/w2/tb/tb_reg8.v
// tb_reg8.v
// Week 2 - Self-checking testbench for reg8.v
// Demonstrates active-low asynchronous reset and rising-edge capture.

`timescale 1ns/1ps

module tb_reg8;

reg        clk;
reg        rst_n;
reg  [7:0] d;
wire [7:0] q;

integer errors;

reg8 dut (
    .clk(clk),
    .rst_n(rst_n),
    .d(d),
    .q(q)
);

// 10 ns clock period. Rising edges occur at 5, 15, 25, 35, ... ns.
initial begin
    clk = 1'b0;
    forever #5 clk = ~clk;
end

task check_q;
    input [7:0] expected_q;
    input [8*64-1:0] tag;
    begin
        if (q !== expected_q) begin
            $display("[FAIL] %0s time=%0t expected_q=%02h got_q=%02h",
                     tag, $time, expected_q, q);
            errors = errors + 1;
        end else begin
            $display("[PASS] %0s time=%0t q=%02h", tag, $time, q);
        end
    end
endtask

initial begin
    $dumpfile("waves/reg8.vcd");
    $dumpvars(0, tb_reg8);

    errors = 0;
    rst_n  = 1'b1;
    d      = 8'h00;

    $display("============================================================");
    $display("Week 2 reg8 functional simulation started");
    $display("Expected behavior: rst_n=0 clears q asynchronously;");
    $display("after release, q captures d only on rising clock edges");
    $display("============================================================");

    // Assert reset between clock edges and verify asynchronous clearing.
    #1;
    rst_n = 1'b0;
    #1;
    check_q(8'h00, "ASYNC_RESET");

    // Keep reset asserted through the first rising edge at 5 ns.
    @(posedge clk);
    #1;
    check_q(8'h00, "RESET_HELD_AT_EDGE");

    // Release reset between rising edges. Release itself must not capture d.
    #6;                 // time = 12 ns
    rst_n = 1'b1;
    d     = 8'hA5;
    #1;
    check_q(8'h00, "RESET_RELEASE_NO_CAPTURE");

    // First normal rising edge at 15 ns captures A5.
    @(posedge clk);
    #1;
    check_q(8'hA5, "CAPTURE_A5");

    // Change d between edges. q must hold until the next rising edge.
    #4;                 // time = 20 ns
    d = 8'h3C;
    #1;
    check_q(8'hA5, "HOLD_BETWEEN_EDGES");

    @(posedge clk);     // 25 ns
    #1;
    check_q(8'h3C, "CAPTURE_3C");

    // Change d again between edges; q still holds.
    #2;
    d = 8'hF0;
    #1;
    check_q(8'h3C, "HOLD_AFTER_D_CHANGE");

    // Assert reset again between clock edges; q must clear immediately.
    #1;
    rst_n = 1'b0;
    #1;
    check_q(8'h00, "ASYNC_RESET_AGAIN");

    // Release reset between edges; release still does not capture.
    #1;
    rst_n = 1'b1;
    d     = 8'h0F;
    #1;
    check_q(8'h00, "SECOND_RELEASE_NO_CAPTURE");

    @(posedge clk);     // 35 ns
    #1;
    check_q(8'h0F, "CAPTURE_0F");

    $display("============================================================");
    if (errors == 0)
        $display("[RESULT] REG8 TEST PASSED");
    else
        $display("[RESULT] REG8 TEST FAILED with %0d error(s)", errors);
    $display("============================================================");

    #4;
    $finish;
end

endmodule

labs/w2/waves/reg8.vcd
$date
   Thu Sep 17 19:45:14 2026
$end

$version
  2025.2
$end

$timescale
  1ps
$end

$scope module tb_reg8 $end
$var reg 1 ! clk $end
$var reg 1 " rst_n $end
$var reg 8 # d [7:0] $end
$var wire 8 $ q [7:0] $end
$var integer 32 % errors [31:0] $end
$scope module dut $end
$var wire 1 & clk $end
$var wire 1 ' rst_n $end
$var wire 8 ( d [7:0] $end
$var reg 8 ) q [7:0] $end
$upscope $end
$scope task check_q $end
$var reg 8 * expected_q [7:0] $end
$var reg 512 + tag [511:0] $end
$upscope $end
$upscope $end
$enddefinitions $end

#0
$dumpvars
0!
1"
b0 #
bx $
b0 %
0&
1'
b0 (
bx )
bx *
bx +
$end

#1000
0"
b0 $
0'
b0 )

#2000
b0 *
b100000101010011010110010100111001000011010111110101001001000101010100110100010101010100 +

#5000
1!
1&

#6000
b10100100100010101010011010001010101010001011111010010000100010101001100010001000101111101000001010101000101111101000101010001000100011101000101 +

#10000
0!
0&

#12000
1"
b10100101 #
1'
b10100101 (

#13000
b10100100100010101010011010001010101010001011111010100100100010101001100010001010100000101010011010001010101111101001110010011110101111101000011010000010101000001010100010101010101001001000101 +

#15000
1!
b10100101 $
1&
b10100101 )

#16000
b10100101 *
b1000011010000010101000001010100010101010101001001000101010111110100000100110101 +

#20000
0!
b111100 #
0&
b111100 (

#21000
b10010000100111101001100010001000101111101000010010001010101010001010111010001010100010101001110010111110100010101000100010001110100010101010011 +

#25000
1!
b111100 $
1&
b111100 )

#26000
b111100 *
b1000011010000010101000001010100010101010101001001000101010111110011001101000011 +

#28000
b11110000 #
b11110000 (

#29000
b1001000010011110100110001000100010111110100000101000110010101000100010101010010010111110100010001011111010000110100100001000001010011100100011101000101 +

#30000
0!
0"
b0 $
0&
0'
b0 )

#31000
b0 *
b100000101010011010110010100111001000011010111110101001001000101010100110100010101010100010111110100000101000111010000010100100101001110 +

#32000
1"
b1111 #
1'
b1111 (

#33000
b1010011010001010100001101001111010011100100010001011111010100100100010101001100010001010100000101010011010001010101111101001110010011110101111101000011010000010101000001010100010101010101001001000101 +

#35000
1!
b1111 $
1&
b1111 )

#36000
b1111 *
b1000011010000010101000001010100010101010101001001000101010111110011000001000110 +

