labs/w7/rtl/fir3_pipe2.v
`timescale 1ns/1ps

// Week 5: one-cycle pipelined 3-tap FIR, beginner-level plain Verilog.
// Stage 1 stores products. Stage 2 adds the stored products and registers y_out.
// Coefficients: h0 = 1, h1 = 2, h2 = 1.
// The delay-state width intentionally matches the Week 4 baseline.
module fir3_pipe2 (
    input  wire              clk,
    input  wire              rst_n,
    input  wire              valid_in,
    input  wire signed [7:0] x_in,
    output reg               valid_out,
    output reg  signed [9:0] y_out
);

    // Same 10-bit signed sample-history convention as Week 4.
    reg signed [9:0] d0, d1, d2;

    wire signed [9:0] x_ext;
    assign x_ext = {{2{x_in[7]}}, x_in};

    reg signed [9:0] p0_s1, p1_s1, p2_s1;
    reg              valid_s1;

    wire signed [9:0] s0_s1;
    wire signed [9:0] y_s1;

    // Stage-2 combinational adder structure from registered products.
    assign s0_s1 = p0_s1 + p1_s1;
    assign y_s1  = s0_s1 + p2_s1;

    always @(posedge clk or negedge rst_n) begin
        if (!rst_n) begin
            d0        <= 10'sd0;
            d1        <= 10'sd0;
            d2        <= 10'sd0;
            p0_s1     <= 10'sd0;
            p1_s1     <= 10'sd0;
            p2_s1     <= 10'sd0;
            y_out     <= 10'sd0;
            valid_s1  <= 1'b0;
            valid_out <= 1'b0;
        end else begin
            // Stage 2 consumes the previous cycle's Stage-1 values.
            if (valid_s1)
                y_out <= y_s1;
            valid_out <= valid_s1;

            // Stage-1 valid follows this cycle's accepted input.
            valid_s1 <= valid_in;

            if (valid_in) begin
                // Products use x_in and PRE-EDGE d0/d1 values.
                p0_s1 <= x_ext;
                p1_s1 <= d0 <<< 1;
                p2_s1 <= d1;

                // Delay line advances only on accepted rising edges.
                d2 <= d1;
                d1 <= d0;
                d0 <= x_ext;
            end
            // When valid_in=0, product registers and d0/d1/d2 hold.
        end
    end

endmodule

labs/w7/tb/tb_fir3_pipe2.v
`timescale 1ns/1ps

module tb_fir3_pipe2;

    reg clk;
    reg rst_n;
    reg valid_in;
    reg signed [7:0] x_in;
    wire valid_out;
    wire signed [9:0] y_out;

    integer errors;

    fir3_pipe2 dut (
        .clk(clk),
        .rst_n(rst_n),
        .valid_in(valid_in),
        .x_in(x_in),
        .valid_out(valid_out),
        .y_out(y_out)
    );

    initial begin
        clk = 1'b0;
        forever #5 clk = ~clk;
    end

    task drive_at_negedge;
        input signed [7:0] sample;
        input              v;
        begin
            @(negedge clk);
            x_in = sample;
            valid_in = v;
        end
    endtask

    task check_output;
        input              e_valid;
        input signed [9:0] e_y;
        input integer      check_y;
        input [8*48-1:0]   label;
        begin
            #1;
            if (valid_out !== e_valid) begin
                $display("[FAIL] %0s valid_out=%0b expected %0b", label, valid_out, e_valid);
                errors = errors + 1;
            end
            if (check_y && y_out !== e_y) begin
                $display("[FAIL] %0s y_out=%0d expected %0d", label, y_out, e_y);
                errors = errors + 1;
            end
            if (valid_out === e_valid && (!check_y || y_out === e_y))
                $display("[PASS] %0s y=%0d valid=%0b", label, y_out, valid_out);
        end
    endtask

    task check_products;
        input signed [9:0] e_p0;
        input signed [9:0] e_p1;
        input signed [9:0] e_p2;
        input              e_v1;
        input [8*48-1:0]   label;
        begin
            #1;
            if (dut.p0_s1 !== e_p0 || dut.p1_s1 !== e_p1 ||
                dut.p2_s1 !== e_p2 || dut.valid_s1 !== e_v1) begin
                $display("[FAIL] %0s products=%0d/%0d/%0d valid_s1=%0b expected %0d/%0d/%0d %0b",
                         label, dut.p0_s1, dut.p1_s1, dut.p2_s1, dut.valid_s1,
                         e_p0, e_p1, e_p2, e_v1);
                errors = errors + 1;
            end else begin
                $display("[PASS] %0s products=%0d/%0d/%0d valid_s1=%0b",
                         label, dut.p0_s1, dut.p1_s1, dut.p2_s1, dut.valid_s1);
            end
        end
    endtask

    task check_delay;
        input signed [9:0] e_d0;
        input signed [9:0] e_d1;
        input signed [9:0] e_d2;
        input [8*48-1:0]   label;
        begin
            #1;
            if (dut.d0 !== e_d0 || dut.d1 !== e_d1 || dut.d2 !== e_d2) begin
                $display("[FAIL] %0s delay state=%0d/%0d/%0d expected %0d/%0d/%0d",
                         label, dut.d0, dut.d1, dut.d2, e_d0, e_d1, e_d2);
                errors = errors + 1;
            end else begin
                $display("[PASS] %0s delay state=%0d/%0d/%0d",
                         label, dut.d0, dut.d1, dut.d2);
            end
        end
    endtask

    initial begin
        errors = 0;
        rst_n = 1'b0;
        valid_in = 1'b0;
        x_in = 8'sd0;

        $dumpfile("waves/fir3_pipe2.vcd");
        $dumpvars(0, tb_fir3_pipe2);

        #2;
        if (dut.d0 !== 0 || dut.d1 !== 0 || dut.d2 !== 0 ||
            dut.p0_s1 !== 0 || dut.p1_s1 !== 0 || dut.p2_s1 !== 0 ||
            dut.valid_s1 !== 0 || valid_out !== 0 || y_out !== 0) begin
            $display("[FAIL] reset did not clear all pipeline state");
            errors = errors + 1;
        end else begin
            $display("[PASS] reset clears delay/product/valid/output state");
        end

        // Reset release alone must not capture input.
        @(negedge clk);
        rst_n = 1'b1;
        x_in = 8'sd77;
        valid_in = 1'b1;
        #1;
        if (dut.d0 !== 0 || dut.valid_s1 !== 0 || valid_out !== 0) begin
            $display("[FAIL] reset release changed registers without a rising edge");
            errors = errors + 1;
        end else begin
            $display("[PASS] reset release does not capture input");
        end
        valid_in = 1'b0;

        // E1: accept x=1. Stage 1 becomes 1/0/0; no output yet.
        drive_at_negedge(8'sd1, 1'b1);
        @(posedge clk);
        check_output(1'b0, 10'sd0, 1, "E1 first accepted sample");
        check_products(10'sd1, 10'sd0, 10'sd0, 1'b1, "E1 product stage");
        check_delay(10'sd1, 10'sd0, 10'sd0, "E1 delay state");

        // E2: accept x=2; output FIR(1)=1; new products 2/2/0.
        drive_at_negedge(8'sd2, 1'b1);
        @(posedge clk);
        check_output(1'b1, 10'sd1, 1, "E2 output sample 1");
        check_products(10'sd2, 10'sd2, 10'sd0, 1'b1, "E2 product stage");
        check_delay(10'sd2, 10'sd1, 10'sd0, "E2 delay state");

        // E3 BUBBLE: invalid x=99 must not advance state or products.
        // Stage 2 still emits FIR(2)=4 from E2's valid Stage-1 products.
        drive_at_negedge(8'sd99, 1'b0);
        @(posedge clk);
        check_output(1'b1, 10'sd4, 1, "E3 bubble emits prior sample 2");
        check_products(10'sd2, 10'sd2, 10'sd0, 1'b0, "E3 bubble product hold");
        check_delay(10'sd2, 10'sd1, 10'sd0, "E3 bubble delay hold");

        // E4: valid traffic resumes with x=3. Because E3 was invalid,
        // valid_out must show a one-cycle output bubble and y_out must hold 4.
        drive_at_negedge(8'sd3, 1'b1);
        @(posedge clk);
        check_output(1'b0, 10'sd4, 1, "E4 delayed output bubble");
        check_products(10'sd3, 10'sd4, 10'sd1, 1'b1, "E4 recovery product stage");
        check_delay(10'sd3, 10'sd2, 10'sd1, "E4 recovery delay state");

        // E5: accept x=4; output FIR(3)=8.
        drive_at_negedge(8'sd4, 1'b1);
        @(posedge clk);
        check_output(1'b1, 10'sd8, 1, "E5 output sample 3");
        check_products(10'sd4, 10'sd6, 10'sd2, 1'b1, "E5 product stage");

        // E6: accept x=5; output FIR(4)=12.
        drive_at_negedge(8'sd5, 1'b1);
        @(posedge clk);
        check_output(1'b1, 10'sd12, 1, "E6 output sample 4");
        check_products(10'sd5, 10'sd8, 10'sd3, 1'b1, "E6 product stage");

        // E7 drain: no new input. Held products produce final 16; valid_s1 becomes 0.
        drive_at_negedge(8'sd0, 1'b0);
        @(posedge clk);
        check_output(1'b1, 10'sd16, 1, "E7 drain final output");
        check_products(10'sd5, 10'sd8, 10'sd3, 1'b0, "E7 held products ignored next cycle");
        check_delay(10'sd5, 10'sd4, 10'sd3, "E7 drain delay hold");

        // Idle: final data may remain stored, but valid_out must be 0.
        drive_at_negedge(8'sd0, 1'b0);
        @(posedge clk);
        check_output(1'b0, 10'sd16, 1, "idle after drain");
        check_products(10'sd5, 10'sd8, 10'sd3, 1'b0, "idle product hold");

        if (errors == 0)
            $display("[RESULT] FIR3_PIPE2 TEST PASSED");
        else
            $display("[RESULT] FIR3_PIPE2 TEST FAILED with %0d error(s)", errors);

        #4;
        $finish;
    end

endmodule

labs/w5/build/xsim/fir3_pipe2/waves/fir3_pipe2.vcd
$date
   Thu Oct  8 15:25:19 2026
$end

$version
  2025.2
  $dumpfile ("waves/fir3_pipe2.vcd") 
$end

$timescale
  1ps
$end

$scope module tb_fir3_pipe2 $end
$var reg 1 ! clk $end
$var reg 1 " rst_n $end
$var reg 1 # valid_in $end
$var reg 8 $ x_in [7:0] $end
$var wire 1 % valid_out $end
$var wire 10 & y_out [9:0] $end
$var integer 32 ' errors [31:0] $end
$scope module dut $end
$var wire 1 ( clk $end
$var wire 1 ) rst_n $end
$var wire 1 * valid_in $end
$var wire 8 + x_in [7:0] $end
$var reg 1 , valid_out $end
$var reg 10 - y_out [9:0] $end
$var reg 10 . d0 [9:0] $end
$var reg 10 / d1 [9:0] $end
$var reg 10 0 d2 [9:0] $end
$var wire 10 1 x_ext [9:0] $end
$var reg 10 2 p0_s1 [9:0] $end
$var reg 10 3 p1_s1 [9:0] $end
$var reg 10 4 p2_s1 [9:0] $end
$var reg 1 5 valid_s1 $end
$var wire 10 6 s0_s1 [9:0] $end
$var wire 10 7 y_s1 [9:0] $end
$upscope $end
$scope task drive_at_negedge $end
$var reg 8 8 sample [7:0] $end
$var reg 1 9 v $end
$upscope $end
$scope task check_output $end
$var reg 1 : e_valid $end
$var reg 10 ; e_y [9:0] $end
$var integer 32 < check_y [31:0] $end
$var reg 384 = label [383:0] $end
$upscope $end
$scope task check_products $end
$var reg 10 > e_p0 [9:0] $end
$var reg 10 ? e_p1 [9:0] $end
$var reg 10 @ e_p2 [9:0] $end
$var reg 1 A e_v1 $end
$var reg 384 B label [383:0] $end
$upscope $end
$scope task check_delay $end
$var reg 10 C e_d0 [9:0] $end
$var reg 10 D e_d1 [9:0] $end
$var reg 10 E e_d2 [9:0] $end
$var reg 384 F label [383:0] $end
$upscope $end
$upscope $end
$enddefinitions $end

#0
$dumpvars
0!
0"
0#
b0 $
0%
b0 &
b0 '
0(
0)
0*
b0 +
0,
b0 -
b0 .
b0 /
b0 0
b0 1
b0 2
b0 3
b0 4
05
b0 6
b0 7
bx 8
x9
x:
bx ;
bx <
bx =
bx >
bx ?
bx @
xA
bx B
bx C
bx D
bx E
bx F
$end

#5000
1!
1(

#10000
0!
1"
1#
b1001101 $
0(
1)
1*
b1001101 +
b1001101 1

#11000
0#
0*
b1 8
19

#15000
1!
1(

#20000
0!
1#
b1 $
0(
1*
b1 +
b1 1

#25000
1!
1(
b1 .
b1 2
15
b1 6
b1 7
0:
b0 ;
b1 <
b10001010011000100100000011001100110100101110010011100110111010000100000011000010110001101100011011001010111000001110100011001010110010000100000011100110110000101101101011100000110110001100101 =

#26000
b1 >
b0 ?
b0 @
1A
b1000101001100010010000001110000011100100110111101100100011101010110001101110100001000000111001101110100011000010110011101100101 B

#27000
b1 C
b0 D
b0 E
b100010100110001001000000110010001100101011011000110000101111001001000000111001101110100011000010111010001100101 F

#28000
b10 8

#30000
0!
b10 $
0(
b10 +
b10 1

#35000
1!
1%
b1 &
1(
1,
b1 -
b10 .
b1 /
b10 2
b10 3
b100 6
b100 7
1:
b1 ;
b10001010011001000100000011011110111010101110100011100000111010101110100001000000111001101100001011011010111000001101100011001010010000000110001 =

#36000
b10 >
b10 ?
b1000101001100100010000001110000011100100110111101100100011101010110001101110100001000000111001101110100011000010110011101100101 B

#37000
b10 C
b1 D
b100010100110010001000000110010001100101011011000110000101111001001000000111001101110100011000010111010001100101 F

#38000
b1100011 8
09

#40000
0!
0#
b1100011 $
0(
0*
b1100011 +
b1100011 1

#45000
1!
b100 &
1(
b100 -
05
b100 ;
b10001010011001100100000011000100111010101100010011000100110110001100101001000000110010101101101011010010111010001110011001000000111000001110010011010010110111101110010001000000111001101100001011011010111000001101100011001010010000000110010 =

#46000
0A
b1000101001100110010000001100010011101010110001001100010011011000110010100100000011100000111001001101111011001000111010101100011011101000010000001101000011011110110110001100100 B

#47000
b100010100110011001000000110001001110101011000100110001001101100011001010010000001100100011001010110110001100001011110010010000001101000011011110110110001100100 F

#48000
b11 8
19

#50000
0!
1#
b11 $
0(
1*
b11 +
b11 1

#55000
1!
0%
1(
0,
b11 .
b10 /
b1 0
b11 2
b100 3
b1 4
15
b111 6
b1000 7
0:
b10001010011010000100000011001000110010101101100011000010111100101100101011001000010000001101111011101010111010001110000011101010111010000100000011000100111010101100010011000100110110001100101 =

#56000
b11 >
b100 ?
b1 @
1A
b1000101001101000010000001110010011001010110001101101111011101100110010101110010011110010010000001110000011100100110111101100100011101010110001101110100001000000111001101110100011000010110011101100101 B

#57000
b11 C
b10 D
b1 E
b100010100110100001000000111001001100101011000110110111101110110011001010111001001111001001000000110010001100101011011000110000101111001001000000111001101110100011000010111010001100101 F

#58000
b100 8

#60000
0!
b100 $
0(
b100 +
b100 1

#65000
1!
1%
b1000 &
1(
1,
b1000 -
b100 .
b11 /
b10 0
b100 2
b110 3
b10 4
b1010 6
b1100 7
1:
b1000 ;
b10001010011010100100000011011110111010101110100011100000111010101110100001000000111001101100001011011010111000001101100011001010010000000110011 =

#66000
b100 >
b110 ?
b10 @
b1000101001101010010000001110000011100100110111101100100011101010110001101110100001000000111001101110100011000010110011101100101 B

#67000
b101 8

#70000
0!
b101 $
0(
b101 +
b101 1

#75000
1!
b1100 &
1(
b1100 -
b101 .
b100 /
b11 0
b101 2
b1000 3
b11 4
b1101 6
b10000 7
b1100 ;
b10001010011011000100000011011110111010101110100011100000111010101110100001000000111001101100001011011010111000001101100011001010010000000110100 =

#76000
b101 >
b1000 ?
b11 @
b1000101001101100010000001110000011100100110111101100100011101010110001101110100001000000111001101110100011000010110011101100101 B

#77000
b0 8
09

#80000
0!
0#
b0 $
0(
0*
b0 +
b0 1

#85000
1!
b10000 &
1(
b10000 -
05
b10000 ;
b10001010011011100100000011001000111001001100001011010010110111000100000011001100110100101101110011000010110110000100000011011110111010101110100011100000111010101110100 =

#86000
0A
b100010100110111001000000110100001100101011011000110010000100000011100000111001001101111011001000111010101100011011101000111001100100000011010010110011101101110011011110111001001100101011001000010000001101110011001010111100001110100001000000110001101111001011000110110110001100101 B

#87000
b101 C
b100 D
b11 E
b1000101001101110010000001100100011100100110000101101001011011100010000001100100011001010110110001100001011110010010000001101000011011110110110001100100 F

#90000
0!
0(

#95000
1!
0%
1(
0,
0:
b1101001011001000110110001100101001000000110000101100110011101000110010101110010001000000110010001110010011000010110100101101110 =

#96000
b110100101100100011011000110010100100000011100000111001001101111011001000111010101100011011101000010000001101000011011110110110001100100 B

